setup.py
money_time_value/__init__.py
money_time_value/bond.py
money_time_value/commonfactors.py
money_time_value.egg-info/PKG-INFO
money_time_value.egg-info/SOURCES.txt
money_time_value.egg-info/dependency_links.txt
money_time_value.egg-info/not-zip-safe
money_time_value.egg-info/top_level.txt