Metadata-Version: 1.0
Name: money-time-value
Version: 0.1
Summary: Time value of money calculations and finding economic equivalance using compound interest formulas
Home-page: UNKNOWN
Author: Zaid Amjad
Author-email: zaidz40@ymail.com
License: UNKNOWN
Platform: UNKNOWN
